Workbook

Sheet README
A1: Digital Wallet Analytics workbook
A2: Source: PaySim mobile money log, 6,362,620 rows, 743 hourly steps (31 days, day 31 has 23 hours). Simulated currency units.
A3: Sheets: Assumptions and Fee_Model are formula driven. KPI, Daily, Type, Hourly, Balance, Segments, Validation hold results exported by python/analysis.py.
A4: Blue cells on Assumptions are inputs. Change them and Fee_Model recalculates.
A5: Revenue is a SCENARIO. The source file has no fee records. Fraud labelled rows earn no fee (assumed reversed).
A6: Fee_Model uses band averages, so it approximates the exact per transaction fee cap. Column 'Exact (Python)' shows the exact base case for comparison.
A7: Balances are pre and post transaction balances on each row, not snapshots. Only 43% of rows reconcile. See Balance and Validation sheets.

Sheet Assumptions
A1: Fee schedule assumptions (illustrative, not observed)
A3: type | B3: gross_rate | C3: partner_rate | D3: cap_per_txn
A4: CASH_IN | B4: 0 | C4: 0 | D4: 5000
A5: CASH_OUT | B5: 0.015 | C5: 0.009 | D5: 5000
A6: TRANSFER | B6: 0.005 | C6: 0.001 | D6: 5000
A7: PAYMENT | B7: 0.01 | C7: 0.004 | D7: 5000
A8: DEBIT | B8: 0.005 | C8: 0.002 | D8: 5000
A10: Gross rate multiplier | B10: 1
A11: Use 0.5 for low, 1.0 base, 1.5 high. Cap applies per transaction to the gross fee.
A12: Partner rate is the cost paid to agents, processors or banks. Net revenue = gross fee minus partner cost.

Sheet Fee_Model
A1: type | B1: amount_band | C1: billable_txns | D1: billable_value | E1: avg_amount | F1: gross_rate | G1: cap | H1: gross_fee | I1: partner_cost | J1: net_fee | L1: Summary by type
A2: CASH_IN | B2: a_0_1k | C2: 4633 | D2: 2296571.2 | E2: =IF(C2=0,0,D2/C2) -> 495.6985 | F2: =INDEX(Assumptions!$B$4:$B$8,MATCH(A2,Assumptions!$A$4:$A$8,0))*Assumptions!$B$10 -> 0 | G2: =INDEX(Assumptions!$D$4:$D$8,MATCH(A2,Assumptions!$A$4:$A$8,0)) -> 5000 | H2: =C2*MIN(E2*F2,G2) -> 0 | I2: =IF(INDEX(Assumptions!$B$4:$B$8,MATCH(A2,Assumptions!$A$4:$A$8,0))=0,0,H2*INDEX(Assumptions!$C$4:$C$8,MATCH(A2,Assumptions!$A$4:$A$8,0))/INDEX(Assumptions!$B$4:$B$8,MATCH(A2,Assumptions!$A$4:$A$8,0))) -> 0 | J2: =H2-I2 -> 0 | L2: type | M2: gross_fee | N2: partner_cost | O2: net_fee | P2: net_share | Q2: Exact net (Python base) | R2: Approx error
A3: CASH_IN | B3: b_1k_5k | C3: 19041 | D3: 57452993 | E3: =IF(C3=0,0,D3/C3) -> 3017.3306 | F3: =INDEX(Assumptions!$B$4:$B$8,MATCH(A3,Assumptions!$A$4:$A$8,0))*Assumptions!$B$10 -> 0 | G3: =INDEX(Assumptions!$D$4:$D$8,MATCH(A3,Assumptions!$A$4:$A$8,0)) -> 5000 | H3: =C3*MIN(E3*F3,G3) -> 0 | I3: =IF(INDEX(Assumptions!$B$4:$B$8,MATCH(A3,Assumptions!$A$4:$A$8,0))=0,0,H3*INDEX(Assumptions!$C$4:$C$8,MATCH(A3,Assumptions!$A$4:$A$8,0))/INDEX(Assumptions!$B$4:$B$8,MATCH(A3,Assumptions!$A$4:$A$8,0))) -> 0 | J3: =H3-I3 -> 0 | L3: CASH_IN | M3: =SUMIFS($H$2:$H$43,$A$2:$A$43,$L3) -> 0 | N3: =SUMIFS($I$2:$I$43,$A$2:$A$43,$L3) -> 0 | O3: =SUMIFS($J$2:$J$43,$A$2:$A$43,$L3) -> 0 | P3: =IF($O$8=0,0,O3/$O$8) -> 0 | Q3: 0 | R3: =IF(Q3=0,0,O3/Q3-1) -> 0
A4: CASH_IN | B4: c_5k_10k | C4: 24018 | D4: 1.8022343e+08 | E4: =IF(C4=0,0,D4/C4) -> 7503.6818 | F4: =INDEX(Assumptions!$B$4:$B$8,MATCH(A4,Assumptions!$A$4:$A$8,0))*Assumptions!$B$10 -> 0 | G4: =INDEX(Assumptions!$D$4:$D$8,MATCH(A4,Assumptions!$A$4:$A$8,0)) -> 5000 | H4: =C4*MIN(E4*F4,G4) -> 0 | I4: =IF(INDEX(Assumptions!$B$4:$B$8,MATCH(A4,Assumptions!$A$4:$A$8,0))=0,0,H4*INDEX(Assumptions!$C$4:$C$8,MATCH(A4,Assumptions!$A$4:$A$8,0))/INDEX(Assumptions!$B$4:$B$8,MATCH(A4,Assumptions!$A$4:$A$8,0))) -> 0 | J4: =H4-I4 -> 0 | L4: CASH_OUT | M4: =SUMIFS($H$2:$H$43,$A$2:$A$43,$L4) -> 5.6060424e+09 | N4: =SUMIFS($I$2:$I$43,$A$2:$A$43,$L4) -> 3.3636254e+09 | O4: =SUMIFS($J$2:$J$43,$A$2:$A$43,$L4) -> 2.2424169e+09 | P4: =IF($O$8=0,0,O4/$O$8) -> 0.63210286 | Q4: 2.1681824e+09 | R4: =IF(Q4=0,0,O4/Q4-1) -> 0.034238165
A5: CASH_IN | B5: d_10k_50k | C5: 198263 | D5: 5.9771709e+09 | E5: =IF(C5=0,0,D5/C5) -> 30147.687 | F5: =INDEX(Assumptions!$B$4:$B$8,MATCH(A5,Assumptions!$A$4:$A$8,0))*Assumptions!$B$10 -> 0 | G5: =INDEX(Assumptions!$D$4:$D$8,MATCH(A5,Assumptions!$A$4:$A$8,0)) -> 5000 | H5: =C5*MIN(E5*F5,G5) -> 0 | I5: =IF(INDEX(Assumptions!$B$4:$B$8,MATCH(A5,Assumptions!$A$4:$A$8,0))=0,0,H5*INDEX(Assumptions!$C$4:$C$8,MATCH(A5,Assumptions!$A$4:$A$8,0))/INDEX(Assumptions!$B$4:$B$8,MATCH(A5,Assumptions!$A$4:$A$8,0))) -> 0 | J5: =H5-I5 -> 0 | L5: DEBIT | M5: =SUMIFS($H$2:$H$43,$A$2:$A$43,$L5) -> 1135996.1 | N5: =SUMIFS($I$2:$I$43,$A$2:$A$43,$L5) -> 454398.44 | O5: =SUMIFS($J$2:$J$43,$A$2:$A$43,$L5) -> 681597.66 | P5: =IF($O$8=0,0,O5/$O$8) -> 0.0001921319 | Q5: 681597.66 | R5: =IF(Q5=0,0,O5/Q5-1) -> 0
A6: CASH_IN | B6: e_50k_100k | C6: 251493 | D6: 1.8840083e+10 | E6: =IF(C6=0,0,D6/C6) -> 74912.952 | F6: =INDEX(Assumptions!$B$4:$B$8,MATCH(A6,Assumptions!$A$4:$A$8,0))*Assumptions!$B$10 -> 0 | G6: =INDEX(Assumptions!$D$4:$D$8,MATCH(A6,Assumptions!$A$4:$A$8,0)) -> 5000 | H6: =C6*MIN(E6*F6,G6) -> 0 | I6: =IF(INDEX(Assumptions!$B$4:$B$8,MATCH(A6,Assumptions!$A$4:$A$8,0))=0,0,H6*INDEX(Assumptions!$C$4:$C$8,MATCH(A6,Assumptions!$A$4:$A$8,0))/INDEX(Assumptions!$B$4:$B$8,MATCH(A6,Assumptions!$A$4:$A$8,0))) -> 0 | J6: =H6-I6 -> 0 | L6: PAYMENT | M6: =SUMIFS($H$2:$H$43,$A$2:$A$43,$L6) -> 2.8093371e+08 | N6: =SUMIFS($I$2:$I$43,$A$2:$A$43,$L6) -> 1.1237348e+08 | O6: =SUMIFS($J$2:$J$43,$A$2:$A$43,$L6) -> 1.6856023e+08 | P6: =IF($O$8=0,0,O6/$O$8) -> 0.047514537 | Q6: 1.6856023e+08 | R6: =IF(Q6=0,0,O6/Q6-1) -> 0
A7: CASH_IN | B7: f_100k_250k | C7: 579328 | D7: 9.7021518e+10 | E7: =IF(C7=0,0,D7/C7) -> 167472.52 | F7: =INDEX(Assumptions!$B$4:$B$8,MATCH(A7,Assumptions!$A$4:$A$8,0))*Assumptions!$B$10 -> 0 | G7: =INDEX(Assumptions!$D$4:$D$8,MATCH(A7,Assumptions!$A$4:$A$8,0)) -> 5000 | H7: =C7*MIN(E7*F7,G7) -> 0 | I7: =IF(INDEX(Assumptions!$B$4:$B$8,MATCH(A7,Assumptions!$A$4:$A$8,0))=0,0,H7*INDEX(Assumptions!$C$4:$C$8,MATCH(A7,Assumptions!$A$4:$A$8,0))/INDEX(Assumptions!$B$4:$B$8,MATCH(A7,Assumptions!$A$4:$A$8,0))) -> 0 | J7: =H7-I7 -> 0 | L7: TRANSFER | M7: =SUMIFS($H$2:$H$43,$A$2:$A$43,$L7) -> 1.4198649e+09 | N7: =SUMIFS($I$2:$I$43,$A$2:$A$43,$L7) -> 2.8397298e+08 | O7: =SUMIFS($J$2:$J$43,$A$2:$A$43,$L7) -> 1.1358919e+09 | P7: =IF($O$8=0,0,O7/$O$8) -> 0.32019047 | Q7: 1.1358919e+09 | R7: =IF(Q7=0,0,O7/Q7-1) -> 0
A8: CASH_IN | B8: g_250k_500k | C8: 296527 | D8: 9.9191561e+10 | E8: =IF(C8=0,0,D8/C8) -> 334511.06 | F8: =INDEX(Assumptions!$B$4:$B$8,MATCH(A8,Assumptions!$A$4:$A$8,0))*Assumptions!$B$10 -> 0 | G8: =INDEX(Assumptions!$D$4:$D$8,MATCH(A8,Assumptions!$A$4:$A$8,0)) -> 5000 | H8: =C8*MIN(E8*F8,G8) -> 0 | I8: =IF(INDEX(Assumptions!$B$4:$B$8,MATCH(A8,Assumptions!$A$4:$A$8,0))=0,0,H8*INDEX(Assumptions!$C$4:$C$8,MATCH(A8,Assumptions!$A$4:$A$8,0))/INDEX(Assumptions!$B$4:$B$8,MATCH(A8,Assumptions!$A$4:$A$8,0))) -> 0 | J8: =H8-I8 -> 0 | L8: Total | M8: =SUM(M3:M7) -> 7.307977e+09 | N8: =SUM(N3:N7) -> 3.7604263e+09 | O8: =SUM(O3:O7) -> 3.5475507e+09 | Q8: =SUM(Q3:Q7) -> 3.4733161e+09 | R8: =IF(Q8=0,0,O8/Q8-1) -> 0.021372828
A9: CASH_IN | B9: h_500k_1M | C9: 25862 | D9: 1.4952818e+10 | E9: =IF(C9=0,0,D9/C9) -> 578177.18 | F9: =INDEX(Assumptions!$B$4:$B$8,MATCH(A9,Assumptions!$A$4:$A$8,0))*Assumptions!$B$10 -> 0 | G9: =INDEX(Assumptions!$D$4:$D$8,MATCH(A9,Assumptions!$A$4:$A$8,0)) -> 5000 | H9: =C9*MIN(E9*F9,G9) -> 0 | I9: =IF(INDEX(Assumptions!$B$4:$B$8,MATCH(A9,Assumptions!$A$4:$A$8,0))=0,0,H9*INDEX(Assumptions!$C$4:$C$8,MATCH(A9,Assumptions!$A$4:$A$8,0))/INDEX(Assumptions!$B$4:$B$8,MATCH(A9,Assumptions!$A$4:$A$8,0))) -> 0 | J9: =H9-I9 -> 0
A10: CASH_IN | B10: i_1M_5M | C10: 119 | D10: 1.4426763e+08 | E10: =IF(C10=0,0,D10/C10) -> 1212333 | F10: =INDEX(Assumptions!$B$4:$B$8,MATCH(A10,Assumptions!$A$4:$A$8,0))*Assumptions!$B$10 -> 0 | G10: =INDEX(Assumptions!$D$4:$D$8,MATCH(A10,Assumptions!$A$4:$A$8,0)) -> 5000 | H10: =C10*MIN(E10*F10,G10) -> 0 | I10: =IF(INDEX(Assumptions!$B$4:$B$8,MATCH(A10,Assumptions!$A$4:$A$8,0))=0,0,H10*INDEX(Assumptions!$C$4:$C$8,MATCH(A10,Assumptions!$A$4:$A$8,0))/INDEX(Assumptions!$B$4:$B$8,MATCH(A10,Assumptions!$A$4:$A$8,0))) -> 0 | J10: =H10-I10 -> 0 | L10: Exact column is valid only when the multiplier is 1.0. Errors come from using band averages with a per transaction cap.
A11: CASH_OUT | B11: a_0_1k | C11: 7187 | D11: 3599282.9 | E11: =IF(C11=0,0,D11/C11) -> 500.80463 | F11: =INDEX(Assumptions!$B$4:$B$8,MATCH(A11,Assumptions!$A$4:$A$8,0))*Assumptions!$B$10 -> 0.015 | G11: =INDEX(Assumptions!$D$4:$D$8,MATCH(A11,Assumptions!$A$4:$A$8,0)) -> 5000 | H11: =C11*MIN(E11*F11,G11) -> 53989.243 | I11: =IF(INDEX(Assumptions!$B$4:$B$8,MATCH(A11,Assumptions!$A$4:$A$8,0))=0,0,H11*INDEX(Assumptions!$C$4:$C$8,MATCH(A11,Assumptions!$A$4:$A$8,0))/INDEX(Assumptions!$B$4:$B$8,MATCH(A11,Assumptions!$A$4:$A$8,0))) -> 32393.546 | J11: =H11-I11 -> 21595.697
A12: CASH_OUT | B12: b_1k_5k | C12: 28781 | D12: 86340524 | E12: =IF(C12=0,0,D12/C12) -> 2999.914 | F12: =INDEX(Assumptions!$B$4:$B$8,MATCH(A12,Assumptions!$A$4:$A$8,0))*Assumptions!$B$10 -> 0.015 | G12: =INDEX(Assumptions!$D$4:$D$8,MATCH(A12,Assumptions!$A$4:$A$8,0)) -> 5000 | H12: =C12*MIN(E12*F12,G12) -> 1295107.9 | I12: =IF(INDEX(Assumptions!$B$4:$B$8,MATCH(A12,Assumptions!$A$4:$A$8,0))=0,0,H12*INDEX(Assumptions!$C$4:$C$8,MATCH(A12,Assumptions!$A$4:$A$8,0))/INDEX(Assumptions!$B$4:$B$8,MATCH(A12,Assumptions!$A$4:$A$8,0))) -> 777064.72 | J12: =H12-I12 -> 518043.14
A13: CASH_OUT | B13: c_5k_10k | C13: 36646 | D13: 2.7469904e+08 | E13: =IF(C13=0,0,D13/C13) -> 7496.0171 | F13: =INDEX(Assumptions!$B$4:$B$8,MATCH(A13,Assumptions!$A$4:$A$8,0))*Assumptions!$B$10 -> 0.015 | G13: =INDEX(Assumptions!$D$4:$D$8,MATCH(A13,Assumptions!$A$4:$A$8,0)) -> 5000 | H13: =C13*MIN(E13*F13,G13) -> 4120485.7 | I13: =IF(INDEX(Assumptions!$B$4:$B$8,MATCH(A13,Assumptions!$A$4:$A$8,0))=0,0,H13*INDEX(Assumptions!$C$4:$C$8,MATCH(A13,Assumptions!$A$4:$A$8,0))/INDEX(Assumptions!$B$4:$B$8,MATCH(A13,Assumptions!$A$4:$A$8,0))) -> 2472291.4 | J13: =H13-I13 -> 1648194.3
A14: CASH_OUT | B14: d_10k_50k | C14: 307014 | D14: 9.2779084e+09 | E14: =IF(C14=0,0,D14/C14) -> 30219.822 | F14: =INDEX(Assumptions!$B$4:$B$8,MATCH(A14,Assumptions!$A$4:$A$8,0))*Assumptions!$B$10 -> 0.015 | G14: =INDEX(Assumptions!$D$4:$D$8,MATCH(A14,Assumptions!$A$4:$A$8,0)) -> 5000 | H14: =C14*MIN(E14*F14,G14) -> 1.3916863e+08 | I14: =IF(INDEX(Assumptions!$B$4:$B$8,MATCH(A14,Assumptions!$A$4:$A$8,0))=0,0,H14*INDEX(Assumptions!$C$4:$C$8,MATCH(A14,Assumptions!$A$4:$A$8,0))/INDEX(Assumptions!$B$4:$B$8,MATCH(A14,Assumptions!$A$4:$A$8,0))) -> 83501176 | J14: =H14-I14 -> 55667451
A15: CASH_OUT | B15: e_50k_100k | C15: 393576 | D15: 2.9482854e+10 | E15: =IF(C15=0,0,D15/C15) -> 74910.191 | F15: =INDEX(Assumptions!$B$4:$B$8,MATCH(A15,Assumptions!$A$4:$A$8,0))*Assumptions!$B$10 -> 0.015 | G15: =INDEX(Assumptions!$D$4:$D$8,MATCH(A15,Assumptions!$A$4:$A$8,0)) -> 5000 | H15: =C15*MIN(E15*F15,G15) -> 4.422428e+08 | I15: =IF(INDEX(Assumptions!$B$4:$B$8,MATCH(A15,Assumptions!$A$4:$A$8,0))=0,0,H15*INDEX(Assumptions!$C$4:$C$8,MATCH(A15,Assumptions!$A$4:$A$8,0))/INDEX(Assumptions!$B$4:$B$8,MATCH(A15,Assumptions!$A$4:$A$8,0))) -> 2.6534568e+08 | J15: =H15-I15 -> 1.7689712e+08
A16: CASH_OUT | B16: f_100k_250k | C16: 917877 | D16: 1.5384309e+11 | E16: =IF(C16=0,0,D16/C16) -> 167607.52 | F16: =INDEX(Assumptions!$B$4:$B$8,MATCH(A16,Assumptions!$A$4:$A$8,0))*Assumptions!$B$10 -> 0.015 | G16: =INDEX(Assumptions!$D$4:$D$8,MATCH(A16,Assumptions!$A$4:$A$8,0)) -> 5000 | H16: =C16*MIN(E16*F16,G16) -> 2.3076463e+09 | I16: =IF(INDEX(Assumptions!$B$4:$B$8,MATCH(A16,Assumptions!$A$4:$A$8,0))=0,0,H16*INDEX(Assumptions!$C$4:$C$8,MATCH(A16,Assumptions!$A$4:$A$8,0))/INDEX(Assumptions!$B$4:$B$8,MATCH(A16,Assumptions!$A$4:$A$8,0))) -> 1.3845878e+09 | J16: =H16-I16 -> 9.2305854e+08
A17: CASH_OUT | B17: g_250k_500k | C17: 490994 | D17: 1.6530146e+11 | E17: =IF(C17=0,0,D17/C17) -> 336666.96 | F17: =INDEX(Assumptions!$B$4:$B$8,MATCH(A17,Assumptions!$A$4:$A$8,0))*Assumptions!$B$10 -> 0.015 | G17: =INDEX(Assumptions!$D$4:$D$8,MATCH(A17,Assumptions!$A$4:$A$8,0)) -> 5000 | H17: =C17*MIN(E17*F17,G17) -> 2454970000 | I17: =IF(INDEX(Assumptions!$B$4:$B$8,MATCH(A17,Assumptions!$A$4:$A$8,0))=0,0,H17*INDEX(Assumptions!$C$4:$C$8,MATCH(A17,Assumptions!$A$4:$A$8,0))/INDEX(Assumptions!$B$4:$B$8,MATCH(A17,Assumptions!$A$4:$A$8,0))) -> 1472982000 | J17: =H17-I17 -> 981988000
A18: CASH_OUT | B18: h_500k_1M | C18: 51006 | D18: 2.9745104e+10 | E18: =IF(C18=0,0,D18/C18) -> 583168.73 | F18: =INDEX(Assumptions!$B$4:$B$8,MATCH(A18,Assumptions!$A$4:$A$8,0))*Assumptions!$B$10 -> 0.015 | G18: =INDEX(Assumptions!$D$4:$D$8,MATCH(A18,Assumptions!$A$4:$A$8,0)) -> 5000 | H18: =C18*MIN(E18*F18,G18) -> 255030000 | I18: =IF(INDEX(Assumptions!$B$4:$B$8,MATCH(A18,Assumptions!$A$4:$A$8,0))=0,0,H18*INDEX(Assumptions!$C$4:$C$8,MATCH(A18,Assumptions!$A$4:$A$8,0))/INDEX(Assumptions!$B$4:$B$8,MATCH(A18,Assumptions!$A$4:$A$8,0))) -> 153018000 | J18: =H18-I18 -> 102012000
A19: CASH_OUT | B19: i_1M_5M | C19: 303 | D19: 4.0873977e+08 | E19: =IF(C19=0,0,D19/C19) -> 1348976.1 | F19: =INDEX(Assumptions!$B$4:$B$8,MATCH(A19,Assumptions!$A$4:$A$8,0))*Assumptions!$B$10 -> 0.015 | G19: =INDEX(Assumptions!$D$4:$D$8,MATCH(A19,Assumptions!$A$4:$A$8,0)) -> 5000 | H19: =C19*MIN(E19*F19,G19) -> 1515000 | I19: =IF(INDEX(Assumptions!$B$4:$B$8,MATCH(A19,Assumptions!$A$4:$A$8,0))=0,0,H19*INDEX(Assumptions!$C$4:$C$8,MATCH(A19,Assumptions!$A$4:$A$8,0))/INDEX(Assumptions!$B$4:$B$8,MATCH(A19,Assumptions!$A$4:$A$8,0))) -> 909000 | J19: =H19-I19 -> 606000
A20: DEBIT | B20: a_0_1k | C20: 6785 | D20: 3491556.1 | E20: =IF(C20=0,0,D20/C20) -> 514.59928 | F20: =INDEX(Assumptions!$B$4:$B$8,MATCH(A20,Assumptions!$A$4:$A$8,0))*Assumptions!$B$10 -> 0.005 | G20: =INDEX(Assumptions!$D$4:$D$8,MATCH(A20,Assumptions!$A$4:$A$8,0)) -> 5000 | H20: =C20*MIN(E20*F20,G20) -> 17457.781 | I20: =IF(INDEX(Assumptions!$B$4:$B$8,MATCH(A20,Assumptions!$A$4:$A$8,0))=0,0,H20*INDEX(Assumptions!$C$4:$C$8,MATCH(A20,Assumptions!$A$4:$A$8,0))/INDEX(Assumptions!$B$4:$B$8,MATCH(A20,Assumptions!$A$4:$A$8,0))) -> 6983.1122 | J20: =H20-I20 -> 10474.668
A21: DEBIT | B21: b_1k_5k | C21: 22798 | D21: 62658585 | E21: =IF(C21=0,0,D21/C21) -> 2748.4246 | F21: =INDEX(Assumptions!$B$4:$B$8,MATCH(A21,Assumptions!$A$4:$A$8,0))*Assumptions!$B$10 -> 0.005 | G21: =INDEX(Assumptions!$D$4:$D$8,MATCH(A21,Assumptions!$A$4:$A$8,0)) -> 5000 | H21: =C21*MIN(E21*F21,G21) -> 313292.93 | I21: =IF(INDEX(Assumptions!$B$4:$B$8,MATCH(A21,Assumptions!$A$4:$A$8,0))=0,0,H21*INDEX(Assumptions!$C$4:$C$8,MATCH(A21,Assumptions!$A$4:$A$8,0))/INDEX(Assumptions!$B$4:$B$8,MATCH(A21,Assumptions!$A$4:$A$8,0))) -> 125317.17 | J21: =H21-I21 -> 187975.76
A22: DEBIT | B22: c_5k_10k | C22: 8065 | D22: 54967584 | E22: =IF(C22=0,0,D22/C22) -> 6815.5715 | F22: =INDEX(Assumptions!$B$4:$B$8,MATCH(A22,Assumptions!$A$4:$A$8,0))*Assumptions!$B$10 -> 0.005 | G22: =INDEX(Assumptions!$D$4:$D$8,MATCH(A22,Assumptions!$A$4:$A$8,0)) -> 5000 | H22: =C22*MIN(E22*F22,G22) -> 274837.92 | I22: =IF(INDEX(Assumptions!$B$4:$B$8,MATCH(A22,Assumptions!$A$4:$A$8,0))=0,0,H22*INDEX(Assumptions!$C$4:$C$8,MATCH(A22,Assumptions!$A$4:$A$8,0))/INDEX(Assumptions!$B$4:$B$8,MATCH(A22,Assumptions!$A$4:$A$8,0))) -> 109935.17 | J22: =H22-I22 -> 164902.75
... A43: TRANSFER | B43: j_5M_plus | C43: 10771 | D43: 1.1470106e+11 | E43: =IF(C43=0,0,D43/C43) -> 10649063 | F43: =INDEX(Assumptions!$B$4:$B$8,MATCH(A43,Assumptions!$A$4:$A$8,0))*Assumptions!$B$10 -> 0.005 | G43: =INDEX(Assumptions!$D$4:$D$8,MATCH(A43,Assumptions!$A$4:$A$8,0)) -> 5000 | H43: =C43*MIN(E43*F43,G43) -> 53855000 | I43: =IF(INDEX(Assumptions!$B$4:$B$8,MATCH(A43,Assumptions!$A$4:$A$8,0))=0,0,H43*INDEX(Assumptions!$C$4:$C$8,MATCH(A43,Assumptions!$A$4:$A$8,0))/INDEX(Assumptions!$B$4:$B$8,MATCH(A43,Assumptions!$A$4:$A$8,0))) -> 10771000 | J43: =H43-I43 -> 43084000

Sheet KPI
A1: metric | B1: value
A2: rows_total | B2: 6362620
A3: window_hours | B3: 743
A4: calendar_days | B4: 31
A5: full_days | B5: 30
A6: txn_count | B6: 6362620
A7: txn_value | B7: 1.1443929e+12
A8: avg_amount | B8: 179861.9
A9: median_amount | B9: 74871.94
A10: billable_txn_count | B10: 6354407
A11: billable_txn_value | B11: 1.1323365e+12
A12: fraud_count | B12: 8213
A13: fraud_value | B13: 1.2056415e+10
... A44: mean_balance_last_reconciled | B44: 1975838.4

Sheet Daily
A1: day | B1: hours_covered | C1: is_full_day | D1: txn_count | E1: txn_value | F1: fraud_count | G1: flagged_count | H1: recon_exception | I1: fraud_value | J1: billable_count | K1: billable_value | L1: gross_revenue | M1: partner_cost | N1: net_revenue | O1: dau | P1: new_customers | Q1: returning_customers | R1: avg_amount | S1: fraud_rate_count | T1: recon_exception_rate | U1: high_volume_day | V1: avg_post_balance | W1: median_post_balance | X1: recon_txn
A2: 1 | B2: 24 | C2: =TRUE() -> TRUE | D2: 574255 | E2: 9.2131866e+10 | F2: 271 | G2: 0 | H2: 312400 | I2: 2.1116383e+08 | J2: 573984 | K2: 9.1920702e+10 | L2: 6.606703e+08 | M2: 3.4202382e+08 | N2: 3.1864648e+08 | O2: 573913 | P2: 573913 | Q2: 0 | R2: 160437.2 | S2: 0.00047191579 | T2: 0.54400919 | U2: =TRUE() -> TRUE | V2: 1997857.1 | W2: 244376.1 | X2: 261601
A3: 2 | B3: 24 | C3: =TRUE() -> TRUE | D3: 455238 | E3: 7.1238642e+10 | F3: 309 | G3: 0 | H3: 257651 | I3: 3.7923969e+08 | J3: 454929 | K3: 7.0859403e+10 | L3: 5.2501997e+08 | M3: 2.7410024e+08 | N3: 2.5091973e+08 | O3: 454879 | P3: 454748 | Q3: 131 | R3: 156486.59 | S3: 0.00067876583 | T3: 0.56596989 | U3: =TRUE() -> TRUE | V3: 2020670.9 | W3: 213642.61 | X3: 197285
A4: 3 | B4: 24 | C4: =TRUE() -> TRUE | D4: 1070 | E4: 4.4708447e+08 | F4: 310 | G4: 0 | H4: 271 | I4: 3.9450886e+08 | J4: 760 | K4: 52575612 | L4: 268076.9 | M4: 133329.45 | N4: 134747.45 | O4: 760 | P4: 760 | Q4: 0 | R4: 417835.96 | S4: 0.28971963 | T4: 0.25327103 | U4: =FALSE() -> FALSE | V4: 1479292.3 | W4: 70781.69 | X4: 489
A5: 4 | B5: 24 | C5: =TRUE() -> TRUE | D5: 28240 | E5: 3.8305474e+09 | F5: 262 | G5: 0 | H5: 13423 | I5: 4.3824682e+08 | J5: 27978 | K5: 3.3923005e+09 | L5: 21344896 | M5: 10362256 | N5: 10982640 | O5: 27978 | P5: 27971 | Q5: 7 | R5: 135642.61 | S5: 0.0092776204 | T5: 0.4753187 | U5: =FALSE() -> FALSE | V5: 1462947.4 | W5: 86693.84 | X5: 14555
A6: 5 | B6: 24 | C6: =TRUE() -> TRUE | D6: 9789 | E6: 1.3251338e+09 | F6: 252 | G6: 0 | H6: 4372 | I6: 2.4498058e+08 | J6: 9537 | K6: 1.0801533e+09 | L6: 6544168.2 | M6: 3053678.6 | N6: 3490489.5 | O6: 9537 | P6: 9532 | Q6: 5 | R6: 135369.68 | S6: 0.025743181 | T6: 0.44662376 | U6: =FALSE() -> FALSE | V6: 1144814.8 | W6: 67749.09 | X6: 5165
A7: 6 | B7: 24 | C7: =TRUE() -> TRUE | D7: 441005 | E7: 7.3409986e+10 | F7: 228 | G7: 0 | H7: 254922 | I7: 3.6723358e+08 | J7: 440777 | K7: 7.3042753e+10 | L7: 5.2525482e+08 | M7: 2.724439e+08 | N7: 2.5281092e+08 | O7: 440734 | P7: 440508 | Q7: 226 | R7: 166460.67 | S7: 0.00051700094 | T7: 0.57804787 | U7: =TRUE() -> TRUE | V7: 2111655.8 | W7: 233570.48 | X7: 185855
A8: 7 | B8: 24 | C8: =TRUE() -> TRUE | D8: 420583 | E8: 6.7070778e+10 | F8: 272 | G8: 0 | H8: 239043 | I8: 4.0179013e+08 | J8: 420311 | K8: 6.6668987e+10 | L8: 4.8422725e+08 | M8: 2.5123749e+08 | N8: 2.3298976e+08 | O8: 420276 | P8: 419988 | Q8: 288 | R8: 159470.97 | S8: 0.00064672134 | T8: 0.56836106 | U8: =TRUE() -> TRUE | V8: 1934799.6 | W8: 212134.03 | X8: 181268
A9: 8 | B9: 24 | C9: =TRUE() -> TRUE | D9: 449637 | E9: 7.0030599e+10 | F9: 278 | G9: 0 | H9: 253639 | I9: 3.5199402e+08 | J9: 449359 | K9: 6.9678604e+10 | L9: 4.9926697e+08 | M9: 2.5829494e+08 | N9: 2.4097203e+08 | O9: 449311 | P9: 448902 | Q9: 409 | R9: 155749.19 | S9: 0.00061827652 | T9: 0.56409726 | U9: =TRUE() -> TRUE | V9: 1972810.8 | W9: 206263.29 | X9: 195722
A10: 9 | B10: 24 | C10: =TRUE() -> TRUE | D10: 417919 | E10: 5.8067765e+10 | F10: 255 | G10: 1 | H10: 230677 | I10: 3.8457125e+08 | J10: 417664 | K10: 5.7683194e+10 | L10: 4.27698e+08 | M10: 2.2305423e+08 | N10: 2.0464377e+08 | O10: 417628 | P10: 417129 | Q10: 499 | R10: 138945.02 | S10: 0.00061016608 | T10: 0.55196581 | U10: =TRUE() -> TRUE | V10: 1897075.5 | W10: 173883.63 | X10: 186989
A11: 10 | B11: 24 | C11: =TRUE() -> TRUE | D11: 392945 | E11: 6.5190352e+10 | F11: 282 | G11: 0 | H11: 227726 | I11: 3.730607e+08 | J11: 392663 | K11: 6.4817291e+10 | L11: 4.5136574e+08 | M11: 2.3119949e+08 | N11: 2.2016625e+08 | O11: 392627 | P11: 392109 | Q11: 518 | R11: 165901.98 | S11: 0.00071765769 | T11: 0.57953658 | U11: =TRUE() -> TRUE | V11: 1912365.1 | W11: 217068.64 | X11: 164939
A12: 11 | B12: 24 | C12: =TRUE() -> TRUE | D12: 417859 | E12: 6.0328662e+10 | F12: 262 | G12: 1 | H12: 236288 | I12: 4.2045688e+08 | J12: 417597 | K12: 5.9908205e+10 | L12: 4.4039097e+08 | M12: 2.2904781e+08 | N12: 2.1134315e+08 | O12: 417557 | P12: 416940 | Q12: 617 | R12: 144375.64 | S12: 0.00062700576 | T12: 0.56547304 | U12: =TRUE() -> TRUE | V12: 1945575 | W12: 202265.52 | X12: 181310
A13: 12 | B13: 24 | C13: =TRUE() -> TRUE | D13: 349776 | E13: 5.7988498e+10 | F13: 298 | G13: 1 | H13: 191929 | I13: 4.2798314e+08 | J13: 349478 | K13: 5.7560515e+10 | L13: 3.2927403e+08 | M13: 1.713965e+08 | N13: 1.5787753e+08 | O13: 349452 | P13: 348880 | Q13: 572 | R13: 165787.53 | S13: 0.00085197383 | T13: 0.54871975 | U13: =TRUE() -> TRUE | V13: 1912191.8 | W13: 156095.97 | X13: 157550
A14: 13 | B14: 24 | C14: =TRUE() -> TRUE | D14: 428583 | E14: 1.3867307e+11 | F14: 242 | G14: 0 | H14: 252162 | I14: 4.2415049e+08 | J14: 428341 | K14: 1.3824892e+11 | L14: 5.2879847e+08 | M14: 2.6253547e+08 | N14: 2.6626299e+08 | O14: 428296 | P14: 427532 | Q14: 764 | R14: 323561.76 | S14: 0.00056465142 | T14: 0.58836211 | U14: =TRUE() -> TRUE | V14: 2184894.5 | W14: 231440.04 | X14: 176179
A15: 14 | B15: 24 | C15: =TRUE() -> TRUE | D15: 397876 | E15: 1.0003736e+11 | F15: 246 | G15: 0 | H15: 232707 | I15: 2.7387183e+08 | J15: 397630 | K15: 9.9763488e+10 | L15: 4.7738136e+08 | M15: 2.3759913e+08 | N15: 2.3978223e+08 | O15: 397595 | P15: 396753 | Q15: 842 | R15: 251428.49 | S15: 0.00061828308 | T15: 0.58487318 | U15: =TRUE() -> TRUE | V15: 2054147.4 | W15: 221970.75 | X15: 164923
A16: 15 | B16: 24 | C16: =TRUE() -> TRUE | D16: 401282 | E16: 7.7472365e+10 | F16: 250 | G16: 0 | H16: 231057 | I16: 3.8999081e+08 | J16: 401032 | K16: 7.7082374e+10 | L16: 4.6264326e+08 | M16: 2.3214914e+08 | N16: 2.3049412e+08 | O16: 401008 | P16: 400107 | Q16: 901 | R16: 193062.15 | S16: 0.00062300327 | T16: 0.57579707 | U16: =TRUE() -> TRUE | V16: 2098623.8 | W16: 210815.81 | X16: 169975
A17: 16 | B17: 24 | C17: =TRUE() -> TRUE | D17: 375594 | E17: 6.7890541e+10 | F17: 252 | G17: 0 | H17: 214478 | I17: 3.3559913e+08 | J17: 375342 | K17: 6.7554942e+10 | L17: 4.2096731e+08 | M17: 2.1470688e+08 | N17: 2.0626044e+08 | O17: 375309 | P17: 374457 | Q17: 852 | R17: 180755.13 | S17: 0.00067093724 | T17: 0.57103681 | U17: =TRUE() -> TRUE | V17: 2004844.4 | W17: 201837.43 | X17: 160864
A18: 17 | B18: 24 | C18: =TRUE() -> TRUE | D18: 425766 | E18: 7.4250134e+10 | F18: 320 | G18: 1 | H18: 249538 | I18: 6.3692845e+08 | J18: 425446 | K18: 7.3613206e+10 | L18: 4.8874128e+08 | M18: 2.4814722e+08 | N18: 2.4059406e+08 | O18: 425400 | P18: 424325 | Q18: 1075 | R18: 174391.88 | S18: 0.00075158655 | T18: 0.58609189 | U18: =TRUE() -> TRUE | V18: 2161932.7 | W18: 219279.78 | X18: 175909
A19: 18 | B19: 24 | C19: =TRUE() -> TRUE | D19: 20999 | E19: 3.7115313e+09 | F19: 268 | G19: 2 | H19: 10475 | I19: 5.4466601e+08 | J19: 20731 | K19: 3.1668653e+09 | L19: 19400674 | M19: 9755575.4 | N19: 9645098.3 | O19: 20731 | P19: 20678 | Q19: 53 | R19: 176748 | S19: 0.012762513 | T19: 0.49883328 | U19: =FALSE() -> FALSE | V19: 1513141.4 | W19: 177745.02 | X19: 10258
A20: 19 | B20: 24 | C20: =TRUE() -> TRUE | D20: 11300 | E20: 1.9368955e+09 | F20: 256 | G20: 0 | H20: 5319 | I20: 4.6072818e+08 | J20: 11044 | K20: 1.4761674e+09 | L20: 9052832.4 | M20: 4547767.1 | N20: 4505065.3 | O20: 11043 | P20: 11020 | Q20: 23 | R20: 171406.69 | S20: 0.022654867 | T20: 0.47070796 | U20: =FALSE() -> FALSE | V20: 1556813.4 | W20: 163929.6 | X20: 5725
A21: 20 | B21: 24 | C21: =TRUE() -> TRUE | D21: 19727 | E21: 3.5963732e+09 | F21: 236 | G21: 0 | H21: 10620 | I21: 2.7668333e+08 | J21: 19491 | K21: 3.3196899e+09 | L21: 20086093 | M21: 9973719.7 | N21: 10112373 | O21: 19491 | P21: 19444 | Q21: 47 | R21: 182307.15 | S21: 0.011963299 | T21: 0.53834846 | U21: =FALSE() -> FALSE | V21: 1310533.8 | W21: 192670.77 | X21: 8871
A22: 21 | B22: 24 | C22: =TRUE() -> TRUE | D22: 24593 | E22: 4.8404213e+09 | F22: 272 | G22: 0 | H22: 13363 | I22: 3.8922262e+08 | J22: 24321 | K22: 4.4511987e+09 | L22: 25271907 | M22: 12314730 | N22: 12957177 | O22: 24321 | P22: 24256 | Q22: 65 | R22: 196821.1 | S22: 0.011060058 | T22: 0.543366 | U22: =FALSE() -> FALSE | V22: 1434317.7 | W22: 193350.92 | X22: 10958
A23: 22 | B23: 24 | C23: =TRUE() -> TRUE | D23: 53437 | E23: 9.5152786e+09 | F23: 256 | G23: 0 | H23: 29140 | I23: 4.0881864e+08 | J23: 53181 | K23: 9.10646e+09 | L23: 53993609 | M23: 26800061 | N23: 27193548 | O23: 53181 | P23: 53029 | Q23: 152 | R23: 178065.36 | S23: 0.0047906881 | T23: 0.54531504 | U23: =FALSE() -> FALSE | V23: 1813752.5 | W23: 186493.35 | X23: 24041
A24: 23 | B24: 24 | C24: =TRUE() -> TRUE | D24: 51012 | E24: 8.194746e+09 | F24: 216 | G24: 0 | H24: 27677 | I24: 219389372 | J24: 50796 | K24: 7.9753566e+09 | L24: 51080578 | M24: 25573976 | N24: 25506602 | O24: 50796 | P24: 50670 | Q24: 126 | R24: 160643.5 | S24: 0.0042342978 | T24: 0.54255861 | U24: =FALSE() -> FALSE | V24: 1615427.3 | W24: 190902.47 | X24: 23119
A25: 24 | B25: 24 | C25: =TRUE() -> TRUE | D25: 32709 | E25: 5.2435094e+09 | F25: 280 | G25: 1 | H25: 17592 | I25: 3.3449124e+08 | J25: 32429 | K25: 4.9090181e+09 | L25: 33451179 | M25: 17085395 | N25: 16365784 | O25: 32429 | P25: 32329 | Q25: 100 | R25: 160307.85 | S25: 0.0085603351 | T25: 0.53783362 | U25: =FALSE() -> FALSE | V25: 1379310.2 | W25: 192324.23 | X25: 14838
A26: 25 | B26: 24 | C26: =TRUE() -> TRUE | D26: 57853 | E26: 9.1774873e+09 | F26: 240 | G26: 1 | H26: 31222 | I26: 3.0820549e+08 | J26: 57613 | K26: 8.8692818e+09 | L26: 57266655 | M26: 29112544 | N26: 28154112 | O26: 57612 | P26: 57440 | Q26: 172 | R26: 158634.6 | S26: 0.0041484452 | T26: 0.53967815 | U26: =FALSE() -> FALSE | V26: 1334248.2 | W26: 185342.12 | X26: 26392
A27: 26 | B27: 24 | C27: =TRUE() -> TRUE | D27: 13885 | E27: 2.2287097e+09 | F27: 272 | G27: 1 | H27: 6797 | I27: 3.9593699e+08 | J27: 13613 | K27: 1.8327727e+09 | L27: 11349555 | M27: 5804557.2 | N27: 5544998.2 | O27: 13613 | P27: 13570 | Q27: 43 | R27: 160512.04 | S27: 0.019589485 | T27: 0.48952107 | U27: =FALSE() -> FALSE | V27: 1513005.5 | W27: 166185.12 | X27: 6817
A28: 27 | B28: 24 | C28: =TRUE() -> TRUE | D28: 8578 | E28: 1.7562688e+09 | F28: 280 | G28: 2 | H28: 4351 | I28: 4.3759579e+08 | J28: 8298 | K28: 1.318673e+09 | L28: 8737933.4 | M28: 4493904.9 | N28: 4244028.5 | O28: 8298 | P28: 8274 | Q28: 24 | R28: 204741.06 | S28: 0.032641641 | T28: 0.50722779 | U28: =FALSE() -> FALSE | V28: 1349351 | W28: 203209.27 | X28: 3949
A29: 28 | B29: 24 | C29: =TRUE() -> TRUE | D29: 14661 | E29: 3.006718e+09 | F29: 248 | G29: 1 | H29: 7353 | I29: 3.7787203e+08 | J29: 14413 | K29: 2.628846e+09 | L29: 14247450 | M29: 7092739 | N29: 7154711.2 | O29: 14413 | P29: 14383 | Q29: 30 | R29: 205082.74 | S29: 0.016915626 | T29: 0.50153468 | U29: =FALSE() -> FALSE | V29: 1476203.9 | W29: 201645.54 | X29: 7061
A30: 29 | B30: 24 | C30: =TRUE() -> TRUE | D30: 54890 | E30: 9.3576365e+09 | F30: 260 | G30: 0 | H30: 29920 | I30: 5.0194677e+08 | J30: 54630 | K30: 8.8556897e+09 | L30: 56887050 | M30: 28829877 | N30: 28057173 | O30: 54629 | P30: 54483 | Q30: 146 | R30: 170479.8 | S30: 0.0047367462 | T30: 0.54509018 | U30: =FALSE() -> FALSE | V30: 1453534.6 | W30: 199925.23 | X30: 24710
A31: 30 | B31: 24 | C31: =TRUE() -> TRUE | D31: 11287 | E31: 1.9959004e+09 | F31: 268 | G31: 1 | H31: 5480 | I31: 4.9700253e+08 | J31: 11019 | K31: 1.4988979e+09 | L31: 11708099 | M31: 6204011.5 | N31: 5504087.6 | O31: 11019 | P31: 10992 | Q31: 27 | R31: 176831.79 | S31: 0.02374413 | T31: 0.48551431 | U31: =FALSE() -> FALSE | V31: 488327.18 | W31: 107950.23 | X31: 5540
A32: 31 | B32: 23 | C32: =FALSE() -> FALSE | D32: 272 | E32: 4.4808623e+08 | F32: 272 | G32: 3 | H32: 3 | I32: 4.4808623e+08 | J32: 0 | K32: 0 | L32: 0 | M32: 0 | N32: 0 | O32: 0 | P32: 0 | Q32: 0 | R32: 1647375.9 | S32: 1 | T32: 0.011029412 | U32: =FALSE() -> FALSE

Sheet Type
A1: type | B1: txn_count | C1: txn_value | D1: avg_amount | E1: median_amount | F1: fraud_count | G1: recon_exception | H1: fraud_value | I1: billable_count | J1: billable_value | K1: gross_revenue | L1: partner_cost | M1: net_revenue | N1: count_share | O1: value_share | P1: fraud_rate_count | Q1: fraud_rate_value | R1: recon_exception_rate | S1: avg_gross_fee_per_billable_txn | T1: gross_fee_pct_of_billable_value
A2: CASH_IN | B2: 1399284 | C2: 2.3636739e+11 | D2: 168920.24 | E2: 143427.71 | F2: 0 | G2: 33 | H2: 0 | I2: 1399284 | J2: 2.3636739e+11 | K2: 0 | L2: 0 | M2: 0 | N2: 0.21992261 | O2: 0.20654391 | P2: 0 | Q2: 0 | R2: 2.358349e-05 | S2: 0 | T2: 0
A3: CASH_OUT | B3: 2237500 | C3: 3.94413e+11 | D3: 176273.96 | E3: 147072.18 | F3: 4116 | G3: 1981123 | H3: 5.9892022e+09 | I3: 2233384 | J3: 3.8842379e+11 | K3: 5.4204559e+09 | L3: 3.2522735e+09 | M3: 2.1681824e+09 | N3: 0.35166331 | O3: 0.34464822 | P3: 0.0018395531 | Q3: 0.015185104 | R3: 0.8854181 | S3: 2427.0147 | T3: 0.013955005
A4: DEBIT | B4: 41432 | C4: 2.2719922e+08 | D4: 5483.6653 | E4: 3048.99 | F4: 0 | G4: 11786 | H4: 0 | I4: 41432 | J4: 2.2719922e+08 | K4: 1135996.1 | L4: 454398.44 | M4: 681597.66 | N4: 0.0065117829 | O4: 0.00019853253 | P4: 0 | Q4: 0 | R4: 0.28446611 | S4: 27.418327 | T4: 0.005
A5: PAYMENT | B5: 2151495 | C5: 2.8093371e+10 | D5: 13057.605 | E5: 9482.19 | F5: 0 | G5: 1101124 | H5: 0 | I5: 2151495 | J5: 2.8093371e+10 | K5: 2.8093371e+08 | L5: 1.1237348e+08 | M5: 1.6856023e+08 | N5: 0.33814608 | O5: 0.024548711 | P5: 0 | Q5: 0 | R5: 0.51179482 | S5: 130.57605 | T5: 0.01
A6: TRANSFER | B6: 532909 | C6: 4.8529199e+11 | D6: 910647.01 | E6: 486308.39 | F6: 4097 | G6: 507529 | H6: 6.0672132e+09 | I6: 528812 | J6: 4.7922477e+11 | K6: 1.4198649e+09 | L6: 2.8397298e+08 | M6: 1.1358919e+09 | N6: 0.08375622 | O6: 0.42406062 | P6: 0.0076879918 | Q6: 0.012502191 | R6: 0.95237461 | S6: 2685.0088 | T6: 0.002962837

Sheet Hourly
A1: hour_of_day | B1: txn_count | C1: txn_value | D1: fraud_count | E1: fraud_rate_count
A2: 0 | B2: 27111 | C2: 3.2004011e+09 | D2: 358 | E2: 0.013204972
A3: 1 | B3: 9018 | C3: 1.5551365e+09 | D3: 372 | E3: 0.041250832
A4: 2 | B4: 2007 | C4: 9.1780753e+08 | D4: 326 | E4: 0.16243149
A5: 3 | B5: 1241 | C5: 4.5267043e+08 | D5: 274 | E5: 0.22078969
A6: 4 | B6: 1641 | C6: 6.3735546e+08 | D6: 366 | E6: 0.22303473
A7: 5 | B7: 3420 | C7: 7.3314078e+08 | D7: 358 | E7: 0.10467836
A8: 6 | B8: 8988 | C8: 1.3426569e+09 | D8: 328 | E8: 0.036493102
A9: 7 | B9: 26915 | C9: 4.7717717e+09 | D9: 368 | E9: 0.013672673
A10: 8 | B10: 283518 | C10: 5.7230312e+10 | D10: 341 | E10: 0.0012027455
A11: 9 | B11: 425729 | C11: 9.0728861e+10 | D11: 375 | E11: 0.00088084204
A12: 10 | B12: 445992 | C12: 8.6836289e+10 | D12: 324 | E12: 0.00072647043
A13: 11 | B13: 483418 | C13: 9.5365235e+10 | D13: 339 | E13: 0.00070125647
... A25: 23 | B25: 71587 | C25: 9133130823 | D25: 300 | E25: 0.004190705

Sheet Frequency
A1: txns_per_customer | B1: customers | C1: share_of_customers
A2: 1 | B2: 6335852 | C2: 0.99853904
A3: 2 | B3: 9255 | C3: 0.0014586008
A4: 3 | B4: 15 | C4: 2.3640207e-06

Sheet Segments
A1: segment | B1: customers | C1: txns | D1: value | E1: gross_revenue | F1: net_revenue | G1: customers_share | H1: value_share | I1: gross_revenue_share | J1: net_revenue_share
A2: 1 Top 1% by value | B2: 63451 | C2: 63683 | D2: 2.4278683e+11 | E2: 3.1750196e+08 | F2: 2.5379761e+08 | G2: 0.0099999653 | H2: 0.21441226 | I2: 0.044578005 | J2: 0.073070692
A3: 2 Next 9% | B3: 571061 | C3: 573481 | D3: 3.4520616e+11 | E3: 1.9350876e+09 | F3: 1.1411626e+09 | G3: 0.090000003 | H3: 0.30486181 | I3: 0.27169074 | J3: 0.32855133
A4: 3 Next 40% | B4: 2538049 | C4: 2542641 | D4: 4.7904215e+11 | E4: 4.2575347e+09 | F4: 1.7749137e+09 | G4: 0.40000003 | H4: 0.42305635 | I4: 0.59776766 | J4: 0.51101416
A5: 4 Bottom 50% | B5: 3172561 | C5: 3174602 | D5: 6.5301386e+10 | E5: 6.1226629e+08 | F5: 3.0344216e+08 | G5: 0.5 | H5: 0.057669592 | I5: 0.085963595 | J5: 0.087363819

Sheet Balance
A1: scope | B1: customers | C1: mean | D1: median | E1: p25 | F1: p75 | G1: p90 | H1: p99 | I1: share_zero
A2: All customers, last post transaction balance | B2: 6345122 | C2: 856010.16 | D2: 0 | E2: 0 | F2: 144733.69 | G2: 1977536.4 | H2: 16179958 | I2: 0.56677397
A3: Reconciled rows only, last post transaction balance | B3: 2751115 | C3: 1975838.4 | D3: 207837.14 | E3: 50694.315 | F3: 1501076.1 | G3: 6751831.4 | H3: 21624625 | I3: 3.6348899e-07

Sheet Fraud_Rules
A1: rule | B1: flagged | C1: true_fraud | D1: precision | E1: recall | F1: f1 | G1: fraud_value_captured_share
A2: R0 System flag (isFlaggedFraud) | B2: 16 | C2: 16 | D2: 1 | E2: 0.001948131 | F2: 0.0038886864 | G2: 0.0064517986
A3: R1 TRANSFER above 200,000 | B3: 409110 | C3: 2740 | D3: 0.0066974652 | E3: 0.33361744 | F3: 0.013131316 | G3: 0.49403849
A4: R2 TRANSFER or CASH_OUT | B4: 2770409 | C4: 8213 | D4: 0.0029645442 | E4: 1 | F4: 0.0059115634 | G4: 1
A5: R3 TRANSFER or CASH_OUT draining the full opening balance | B5: 8018 | C5: 8018 | D5: 1 | E5: 0.97625715 | F5: 0.98798595 | G5: 0.87736556

Sheet Validation
A1: check | B1: result | C1: expected | D1: status | E1: note
A2: Row count equals file data lines | B2: 6362620 | C2: 6362620 | D2: PASS
A3: Null values across all columns | B3: 0 | C3: 0 | D3: PASS
A4: Negative amounts | B4: 0 | C4: 0 | D4: PASS
A5: Zero amounts | B5: 16 | C5: 0 | D5: REVIEW | E5: Zero value rows are all fraud labelled cash outs
A6: Duplicate rows on step, type, amount, customer, destination | B6: 0 | C6: 0 | D6: PASS | E6: No retries or duplicates detectable
A7: File sorted by step (needed for last observation logic) | B7: True | C7: True | D7: PASS
A8: Distinct hourly steps | B8: 743 | C8: 743 | D8: PASS
A9: Calendar days covered (step / 24) | B9: 31 | C9: 31 | D9: PASS | E9: Day 31 holds 23 hours only
A10: Distinct transaction types | B10: 5 | C10: 5 | D10: PASS
A11: Fraud labelled rows only in TRANSFER and CASH_OUT | B11: True | C11: True | D11: PASS
A12: Flagged rows are all fraud labelled | B12: True | C12: True | D12: PASS
A13: Merchant destinations only on PAYMENT | B13: True | C13: True | D13: PASS
A14: Originator balance reconciles to amount | B14: 0.4339 | C14: 1.0000 | D14: REVIEW | E14: Pre and post balances reconcile for a minority of rows; see balance section
A15: Debit rows from an account with zero opening balance | B15: 2088969 | C15: 0 | D15: REVIEW | E15: Not possible in a live ledger
A16: Debit rows where amount exceeds opening balance | B16: 3601543 | C16: 0 | D16: REVIEW | E16: Overdraft or unreliable balance field
A17: Customer destination balance reconciles to amount | B17: 0.6028 | C17: 1.0000 | D17: REVIEW | E17: Destination balances not usable
